bluetooth_mesh/bluez/__init__.py
bluetooth_mesh/bluez/application.py
bluetooth_mesh/bluez/interfaces.py
bluetooth_mesh/bluez/tokenring.py
bluetooth_mesh/bluez/utils.py
bluetooth_mesh/bluez/apps/__init__.py
bluetooth_mesh/bluez/apps/hookspecs.py
bluetooth_mesh/bluez/apps/meshcli.py
bluetooth_mesh/bluez/apps/mixins.py
bluetooth_mesh/bluez/models/__init__.py
bluetooth_mesh/bluez/models/base.py
bluetooth_mesh/bluez/models/models.py
bluetooth_mesh_bluez-0.9.2.dist-info/licenses/LICENSE
bluetooth_mesh_bluez-0.9.2.dist-info/METADATA
bluetooth_mesh_bluez-0.9.2.dist-info/WHEEL
bluetooth_mesh_bluez-0.9.2.dist-info/entry_points.txt
bluetooth_mesh_bluez-0.9.2.dist-info/top_level.txt
bluetooth_mesh_bluez-0.9.2.dist-info/RECORD
