Metadata-Version: 2.4
Name: bluetooth-mesh-bluez
Version: 0.9.2
Author-email: Michał Lowas-Rzechonek <michal.lowas-rzechonek@silvair.com>, Amadeusz Herzog <amadeusz.hercog@silvair.com>, Jakub Witowski <jakub.witowski@silvair.com>, Kamil Janowski <kamil.janowski@silvair.com>, Przemysław Fierek <przemyslaw.fierek@silvair.com>, Rafał Gajda <rafal.gajda@silvair.com>
Classifier: Development Status :: 4 - Beta
Classifier: Intended Audience :: Developers
Classifier: License :: OSI Approved :: GNU General Public License v2 (GPLv2)
Classifier: Operating System :: POSIX :: Linux
Classifier: Programming Language :: Python :: 3 :: Only
Classifier: Programming Language :: Python :: Implementation :: CPython
Classifier: Topic :: System :: Networking
License-File: LICENSE
Requires-Dist: bluetooth-mesh-messages>=0.9
Requires-Dist: bluetooth-mesh-network>=0.9
Requires-Dist: dbus-next>=0.2.1
Requires-Dist: pluggy>=0.13.1
Requires-Dist: marshmallow<4.0,>=3.0.1
Provides-Extra: test
Requires-Dist: asynctest; extra == "test"
Requires-Dist: black; extra == "test"
Requires-Dist: isort; extra == "test"
Requires-Dist: pytest; extra == "test"
Requires-Dist: pytest-asyncio; extra == "test"
Requires-Dist: ruff; extra == "test"
Provides-Extra: cli
Requires-Dist: prompt-toolkit==2.0.10; extra == "cli"
Dynamic: license-file
